bohrium-0.9.2.post67.data/purelib/bohrium/__init__.py
bohrium-0.9.2.post67.data/purelib/bohrium/__main__.py
bohrium-0.9.2.post67.data/purelib/bohrium/_bh.so
bohrium-0.9.2.post67.data/purelib/bohrium/_info.py
bohrium-0.9.2.post67.data/purelib/bohrium/_util.so
bohrium-0.9.2.post67.data/purelib/bohrium/array_create.py
bohrium-0.9.2.post67.data/purelib/bohrium/array_manipulation.py
bohrium-0.9.2.post67.data/purelib/bohrium/backend_messaging.py
bohrium-0.9.2.post67.data/purelib/bohrium/bh_info.py
bohrium-0.9.2.post67.data/purelib/bohrium/bhary.so
bohrium-0.9.2.post67.data/purelib/bohrium/blas.py
bohrium-0.9.2.post67.data/purelib/bohrium/bohriumify.py
bohrium-0.9.2.post67.data/purelib/bohrium/concatenate.py
bohrium-0.9.2.post67.data/purelib/bohrium/config.ini
bohrium-0.9.2.post67.data/purelib/bohrium/contexts.py
bohrium-0.9.2.post67.data/purelib/bohrium/disk_io.py
bohrium-0.9.2.post67.data/purelib/bohrium/dual.py
bohrium-0.9.2.post67.data/purelib/bohrium/interop_numpy.py
bohrium-0.9.2.post67.data/purelib/bohrium/interop_pycuda.py
bohrium-0.9.2.post67.data/purelib/bohrium/interop_pyopencl.py
bohrium-0.9.2.post67.data/purelib/bohrium/lapack.py
bohrium-0.9.2.post67.data/purelib/bohrium/linalg.py
bohrium-0.9.2.post67.data/purelib/bohrium/loop.py
bohrium-0.9.2.post67.data/purelib/bohrium/masking.py
bohrium-0.9.2.post67.data/purelib/bohrium/numpy_backport.py
bohrium-0.9.2.post67.data/purelib/bohrium/opencv.py
bohrium-0.9.2.post67.data/purelib/bohrium/random123.so
bohrium-0.9.2.post67.data/purelib/bohrium/reorganization.py
bohrium-0.9.2.post67.data/purelib/bohrium/signal.py
bohrium-0.9.2.post67.data/purelib/bohrium/stdviews.py
bohrium-0.9.2.post67.data/purelib/bohrium/summations.py
bohrium-0.9.2.post67.data/purelib/bohrium/ufuncs.so
bohrium-0.9.2.post67.data/purelib/bohrium/visualization.py
bohrium-0.9.2.post67.data/purelib/bohrium/include/Random123/MicroURNG.hpp
bohrium-0.9.2.post67.data/purelib/bohrium/include/Random123/ReinterpretCtr.hpp
bohrium-0.9.2.post67.dist-info/DESCRIPTION.rst
bohrium-0.9.2.post67.dist-info/METADATA
bohrium-0.9.2.post67.dist-info/RECORD
bohrium-0.9.2.post67.dist-info/WHEEL
bohrium-0.9.2.post67.dist-info/metadata.json
bohrium-0.9.2.post67.dist-info/top_level.txt
