Metadata-Version: 2.0
Name: bohrium
Version: 0.9.2.post67
Summary: Bohrium NumPy
Home-page: http://www.bh107.org
Author: Mads R. B. Kristensen
Author-email: madsbk@gmail.com
License: LGPLv3
Keywords: Bohrium,bh107,Python,C,CUDA,OpenCL
Platform: Linux
Platform: OSX
Classifier: Development Status :: 4 - Beta
Classifier: Intended Audience :: Developers
Classifier: Intended Audience :: Science/Research
Classifier: Topic :: Scientific/Engineering
Classifier: Topic :: Software Development
Classifier: Operating System :: MacOS
Classifier: Operating System :: POSIX
Classifier: Operating System :: Unix
Classifier: License :: OSI Approved :: GNU General Public License (GPL)
Classifier: Programming Language :: Python :: 2.7
Classifier: Programming Language :: Python :: 3
Classifier: Programming Language :: C
Classifier: Programming Language :: Python :: Implementation :: CPython
Requires-Dist: numpy (>=1.13)
